poresim/__init__.py
poresim/actuate.py
poresim/analyze.py
poresim/benchmark.py
poresim/box.py
poresim/construct.py
poresim/parameter.py
poresim/simulate.py
poresim/topology.py
poresim/utils.py
poresim/templates/auto_dens.py
poresim/templates/auto_dens_box.py
poresim/templates/config.yml
poresim/templates/sort.py
poresim-0.3.0.dist-info/licenses/LICENSE
tests/__init__.py
tests/test_simple.py
poresim-0.3.0.dist-info/METADATA
poresim-0.3.0.dist-info/WHEEL
poresim-0.3.0.dist-info/top_level.txt
poresim-0.3.0.dist-info/RECORD
