Metadata-Version: 2.4
Name: poresim
Version: 0.3.0
Summary: Pore system simulation generator.
Home-page: https://github.com/PoreMS/PoreSim
Author: Hamzeh Kraus
Author-email: kraus@itt.uni-stuttgart.de
Classifier: Programming Language :: Python :: 3
Classifier: License :: OSI Approved :: GNU General Public License v3 (GPLv3)
Classifier: Operating System :: OS Independent
Requires-Python: >=3.5
License-File: LICENSE
Requires-Dist: numpy
Requires-Dist: pyyaml
Requires-Dist: jinja2==3.0.3
Dynamic: author
Dynamic: author-email
Dynamic: classifier
Dynamic: description
Dynamic: description-content-type
Dynamic: home-page
Dynamic: license-file
Dynamic: requires-dist
Dynamic: requires-python
Dynamic: summary
